{
  "main": {
    "id": "98ad8450aa1874be",
    "type": "split",
    "children": [
      {
        "id": "7f8364230cb89bbb",
        "type": "tabs",
        "children": [
          {
            "id": "ffff39c68fb85ae1",
            "type": "leaf",
            "state": {
              "type": "markdown",
              "state": {
                "file": "agents/Adele/modes/code-writer.md",
                "mode": "source",
                "source": false
              },
              "icon": "lucide-file",
              "title": "code-writer"
            }
          }
        ]
      }
    ],
    "direction": "vertical"
  },
  "left": {
    "id": "8b15399e1c989930",
    "type": "split",
    "children": [
      {
        "id": "187092ed1f2c627f",
        "type": "tabs",
        "children": [
          {
            "id": "bf2c677e8837eeaa",
            "type": "leaf",
            "state": {
              "type": "file-explorer",
              "state": {
                "sortOrder": "alphabetical",
                "autoReveal": false
              },
              "icon": "lucide-folder-closed",
              "title": "Files"
            }
          },
          {
            "id": "d2604ff006fb70db",
            "type": "leaf",
            "state": {
              "type": "search",
              "state": {
                "query": "",
                "matchingCase": false,
                "explainSearch": false,
                "collapseAll": false,
                "extraContext": false,
                "sortOrder": "alphabetical"
              },
              "icon": "lucide-search",
              "title": "Search"
            }
          },
          {
            "id": "8533d176006b9ec3",
            "type": "leaf",
            "state": {
              "type": "bookmarks",
              "state": {},
              "icon": "lucide-bookmark",
              "title": "Bookmarks"
            }
          }
        ]
      }
    ],
    "direction": "horizontal",
    "width": 300
  },
  "right": {
    "id": "f452adc7a57bb8b7",
    "type": "split",
    "children": [
      {
        "id": "55e14c5168cedf36",
        "type": "tabs",
        "children": [
          {
            "id": "19fdf62125913ec4",
            "type": "leaf",
            "state": {
              "type": "backlink",
              "state": {
                "file": "project/v1.3-release.md",
                "collapseAll": false,
                "extraContext": false,
                "sortOrder": "alphabetical",
                "showSearch": false,
                "searchQuery": "",
                "backlinkCollapsed": false,
                "unlinkedCollapsed": true
              },
              "icon": "links-coming-in",
              "title": "Backlinks for v1.3-release"
            }
          },
          {
            "id": "9e4a9f440ba47473",
            "type": "leaf",
            "state": {
              "type": "outgoing-link",
              "state": {
                "file": "project/v1.3-release.md",
                "linksCollapsed": false,
                "unlinkedCollapsed": true
              },
              "icon": "links-going-out",
              "title": "Outgoing links from v1.3-release"
            }
          },
          {
            "id": "107e4db70f77355b",
            "type": "leaf",
            "state": {
              "type": "tag",
              "state": {
                "sortOrder": "frequency",
                "useHierarchy": true,
                "showSearch": false,
                "searchQuery": ""
              },
              "icon": "lucide-tags",
              "title": "Tags"
            }
          },
          {
            "id": "bae2d9399a4b25ec",
            "type": "leaf",
            "state": {
              "type": "all-properties",
              "state": {
                "sortOrder": "frequency",
                "showSearch": false,
                "searchQuery": ""
              },
              "icon": "lucide-archive",
              "title": "All properties"
            }
          },
          {
            "id": "ba52de6324591d69",
            "type": "leaf",
            "state": {
              "type": "outline",
              "state": {
                "file": "project/v1.3-release.md",
                "followCursor": false,
                "showSearch": false,
                "searchQuery": ""
              },
              "icon": "lucide-list",
              "title": "Outline of v1.3-release"
            }
          }
        ]
      }
    ],
    "direction": "horizontal",
    "width": 300,
    "collapsed": true
  },
  "left-ribbon": {
    "hiddenItems": {
      "switcher:Open quick switcher": false,
      "graph:Open graph view": false,
      "canvas:Create new canvas": false,
      "daily-notes:Open today's daily note": false,
      "templates:Insert template": false,
      "command-palette:Open command palette": false,
      "bases:Create new base": false
    }
  },
  "active": "ffff39c68fb85ae1",
  "lastOpenFiles": [
    "agents/Adele/archive/inbox/b427bed7-msg-verify-process-leak-fix.md",
    "agents/Charlie/archive/inbox/ad295aa8-verify-process-leak-fix.md",
    "agents/Adele/inbox/b427bed7-msg-verify-process-leak-fix.md",
    "agents/Adele/archive/inbox/f0ce05e3-msg-fix-zombie-worktrees.md",
    "agents/Emma/archive/inbox/71c7474b-fix-zombie-worktrees.md",
    "agents/Adele/inbox/f0ce05e3-msg-fix-zombie-worktrees.md",
    "agents/Charlie/modes/test-writer.md",
    "agents/Charlie/modes/reviewer.md",
    "agents/Charlie/modes/orchestrator.md",
    "agents/Charlie/modes/planner.md",
    "agents/Charlie/modes/inquisitor.md",
    "agents/Charlie/modes/judge.md",
    "agents/Charlie/modes/docs-writer.md",
    "agents/Charlie/modes/code-writer.md",
    "agents/Charlie/modes/co-thinker.md",
    "agents/Charlie/modes",
    "_system/audit/2026/2026-03-26-ceaba17c-2ee3-4978-a01a-c47dce44340a.json",
    "agents/Charlie/inbox/ad295aa8-verify-process-leak-fix.md",
    "agents/Dexter/archive/inbox/f398b7cf-verify-process-leak-fix.md",
    "agents/Emma/modes/test-writer.md",
    "agents/Emma/modes/reviewer.md",
    "agents/Emma/modes/planner.md",
    "agents/Emma/modes/orchestrator.md",
    "agents/Emma/modes/judge.md",
    "agents/Emma/modes/inquisitor.md",
    "agents/Emma/modes/docs-writer.md",
    "agents/Emma/modes/code-writer.md",
    "agents/Emma/modes/co-thinker.md",
    "agents/Emma/modes",
    "_system/audit/2026/2026-03-26-58fb8f33-5aa6-4e50-b824-824ba5401e44.json",
    "agents/Charlie/archive/20260326-231126",
    "_system/audit/2026/2026-03-26-dc4f0c81-ca9e-4d2b-b666-7b89079d6d0c.json",
    "agents/Brian/modes",
    "_system/audit/2026/2026-03-26-f8549630-b76e-44d5-a8b9-2320aeae4aad.json",
    "_system/audit/2026/2026-03-26-9e33012f-4d6b-43ae-b6d5-9d54c5888499.json",
    "_system/audit/2026/2026-03-26-69c0187e-1b82-43c6-8e86-714c668df760.json"
  ]
}